barviz/Attributes.py
barviz/Collection.py
barviz/Scrawler.py
barviz/Simplex.py
barviz/SimplexBuilder.py
barviz/__init__.py
barviz/version.py
barviz-1.2.2.dist-info/LICENSE
barviz-1.2.2.dist-info/METADATA
barviz-1.2.2.dist-info/WHEEL
barviz-1.2.2.dist-info/top_level.txt
barviz-1.2.2.dist-info/RECORD
