Metadata-Version: 2.1
Name: barviz
Version: 1.2.2
Summary: A simple python module to visualize barycentric data.
Home-page: https://gricad-gitlab.univ-grenoble-alpes.fr/pjluc/barviz-mod
Author: JL Parouty
Classifier: Programming Language :: Python :: 3
Classifier: License :: OSI Approved :: MIT License
Classifier: Operating System :: OS Independent
Requires-Python: >=3.6
License-File: LICENSE
Requires-Dist: plotly (>=5.4)
Requires-Dist: numpy
Requires-Dist: kaleido
Requires-Dist: pandas
